centpy/__init__.py
centpy/_helpers.py
centpy/equations.py
centpy/parameters.py
centpy/solver1d.py
centpy/solver2d.py
centpy-0.1.dist-info/LICENSE
centpy-0.1.dist-info/METADATA
centpy-0.1.dist-info/WHEEL
centpy-0.1.dist-info/top_level.txt
centpy-0.1.dist-info/RECORD
