Metadata-Version: 2.1
Name: centpy
Version: 0.1
Summary: A numerical solver for conservation laws based on central schemes
Home-page: https://github.com/AnilZen/centpy
Author: Anil Zenginoglu
Author-email: anil@umd.edu
License: UNKNOWN
Platform: UNKNOWN
Classifier: Programming Language :: Python :: 3
Classifier: License :: OSI Approved :: MIT License
Classifier: Operating System :: OS Independent
Requires-Python: >=3.6
Requires-Dist: numpy
